{
    "n_data": 500000,
    "load_data": false,
    "data_type": "random-2masstriangle",
    "n_test_data": 10,
    "batch_size": 1024,
    "basis_order": 32,
    "n_masses": 2,
    "n_dimensions": 2,
    "detectors": [
        "H1",
        "L1",
        "V1"
    ],
    "transformer_layers": {
        "embed_dim": 48,
        "num_heads": 12,
        "num_layers": 6
    },
    "sample_rate": 32,
    "duration": 1,
    "plot_sample_rate": 32,
    "n_epochs": 10000,
    "window": "hann",
    "basis_type": "fourier",
    "fourier_exp_weight": 0.0,
    "window_acceleration": "hann",
    "window_strain": true,
    "spherical_coords": false,
    "learning_rate": 0.0005,
    "device": "cuda:0",
    "flow_model_type": "nsf",
    "nsplines": 16,
    "ntransforms": 16,
    "n_context": 256,
    "hidden_features": [
        512,
        512,
        512
    ],
    "root_dir": "/path/to/outputdir",
    "custom_flow": false,
    "data_dir": "./data",
    "fourier_weight": 0.0,
    "noise_variance": 0.0,
    "snr": false,
    "prior_args": {
        "masses_min": 0.5,
        "masses_max": 1.0,
	"sky_position": [3.14159, 1.5707]
    }
}
